LICENSE
MANIFEST.in
README.rst
setup.py
mythical/__init__.py
mythical/bank_account.py
mythical/credit_card.py
mythical/merchant.py
mythical/mime.py
mythical/suite.py
mythical.egg-info/PKG-INFO
mythical.egg-info/SOURCES.txt
mythical.egg-info/dependency_links.txt
mythical.egg-info/not-zip-safe
mythical.egg-info/requires.txt
mythical.egg-info/top_level.txt
mythical/packages/__init__.py