Metadata-Version: 1.1
Name: mythical
Version: 0.2.0
Summary: Mythical client
Home-page: https://github.com/verygoodgroup/mythical-client
Author: Franz Sanchez
Author-email: dev+mythical@vgs.io
License: UNKNOWN
Platform: any
Classifier: Development Status :: 4 - Beta
Classifier: Intended Audience :: Developers
Classifier: Natural Language :: English
Classifier: License :: OSI Approved :: ISC License (ISCL)
Classifier: Programming Language :: Python
Classifier: Programming Language :: Python :: 2.7
